pygnparser/__init__.py
pygnparser/package_metadata.py
pygnparser/pygnparser/__init__.py
pygnparser/pygnparser/gnparser.py
pygnparser/utils/__init__.py
pygnparser/utils/pygnparser_utils.py
pygnparser/utils/result.py
test/__init__.py
test/test-parse.py
pyGNparser-0.0.5.dist-info/LICENSE.txt
pyGNparser-0.0.5.dist-info/METADATA
pyGNparser-0.0.5.dist-info/WHEEL
pyGNparser-0.0.5.dist-info/top_level.txt
pyGNparser-0.0.5.dist-info/RECORD
