Metadata-Version: 2.1
Name: pyGNparser
Version: 0.0.5
Summary: Python client for GNparser
Home-page: http://github.com/gnames/pyGNparser
Download-URL: https://github.com/gnames/pyGNparser/archive/refs/tags/v0.0.5.tar.gz
Author: Geoff Ower
Author-email: gdower@illinois.edu
License: MIT
Keywords: biodiversity,scientific names,parser,nomenclature,taxonomy,API,web-services,species,natural history,taxonomists,biologists,Global Names
Classifier: Development Status :: 5 - Production/Stable
Classifier: Intended Audience :: Science/Research
Classifier: Topic :: Scientific/Engineering :: Bio-Informatics
Classifier: Natural Language :: English
Classifier: License :: OSI Approved :: MIT License
Classifier: Programming Language :: Python
Classifier: Programming Language :: Python :: 3.9
Classifier: Programming Language :: Python :: 3.10
Classifier: Programming Language :: Python :: 3.11
Classifier: Programming Language :: Python :: 3.12
Classifier: Programming Language :: Python :: 3.13
License-File: LICENSE.txt
Requires-Dist: requests >2.7
Provides-Extra: dev
Requires-Dist: codecov ; extra == 'dev'
Requires-Dist: pytest ; extra == 'dev'
Requires-Dist: pytest-cov ; extra == 'dev'
Requires-Dist: sphinx >7.2.0 ; extra == 'dev'
Requires-Dist: sphinx-issues ; extra == 'dev'
Requires-Dist: sphinx-rtd-theme ; extra == 'dev'
Requires-Dist: twine ; extra == 'dev'
Requires-Dist: wheel ; extra == 'dev'
